HyperGP/CMakeLists.txt
HyperGP/__init__.py
HyperGP/workflow.py
HyperGP/Makefile
HyperGP/base/prog_basic.py
HyperGP/base/base_struct.py
HyperGP/base/tree_basic.py
HyperGP/base/__init__.py
HyperGP/base/func_basic.py
HyperGP/base/pop_basic.py
HyperGP/base/__pycache__/ops.cpython-311.pyc
HyperGP/base/__pycache__/ops.cpython-36.pyc
HyperGP/base/__pycache__/base_struct.cpython-312.pyc
HyperGP/base/__pycache__/tree_basic.cpython-310.pyc
HyperGP/base/__pycache__/__init__.cpython-313.pyc
HyperGP/base/__pycache__/func_basic.cpython-311.pyc
HyperGP/base/__pycache__/tree_basic.cpython-36.pyc
HyperGP/base/__pycache__/prog_basic.cpython-311.pyc
HyperGP/base/__pycache__/func_basic.cpython-312.pyc
HyperGP/base/__pycache__/__init__.cpython-36.pyc
HyperGP/base/__pycache__/base_struct.cpython-36.pyc
HyperGP/base/__pycache__/base_struct.cpython-313.pyc
HyperGP/base/__pycache__/base_struct.cpython-37.pyc
HyperGP/base/__pycache__/tree_basic.cpython-39.pyc
HyperGP/base/__pycache__/func_basic.cpython-39.pyc
HyperGP/base/__pycache__/prog_basic.cpython-310.pyc
HyperGP/base/__pycache__/tree_basic.cpython-311.pyc
HyperGP/base/__pycache__/ops.cpython-37.pyc
HyperGP/base/__pycache__/tree_basic.cpython-313.pyc
HyperGP/base/__pycache__/pop_basic.cpython-36.pyc
HyperGP/base/__pycache__/base_struct.cpython-310.pyc
HyperGP/base/__pycache__/prog_basic.cpython-312.pyc
HyperGP/base/__pycache__/prog_basic.cpython-39.pyc
HyperGP/base/__pycache__/__init__.cpython-39.pyc
HyperGP/base/__pycache__/func_basic.cpython-310.pyc
HyperGP/base/__pycache__/__init__.cpython-311.pyc
HyperGP/base/__pycache__/pop_basic.cpython-312.pyc
HyperGP/base/__pycache__/pop_basic.cpython-39.pyc
HyperGP/base/__pycache__/func_basic.cpython-36.pyc
HyperGP/base/__pycache__/prog_basic.cpython-36.pyc
HyperGP/base/__pycache__/pop_basic.cpython-310.pyc
HyperGP/base/__pycache__/ops.cpython-39.pyc
HyperGP/base/__pycache__/pop_basic.cpython-311.pyc
HyperGP-0.1.3.post5.dist-info/RECORD
HyperGP-0.1.3.post5.dist-info/METADATA
HyperGP-0.1.3.post5.dist-info/WHEEL
HyperGP-0.1.3.post5.dist-info/top_level.txt
HyperGP-0.1.3.post5.dist-info/LICENSE
